hpvsim/__init__.py
hpvsim/analysis.py
hpvsim/base.py
hpvsim/calibration.py
hpvsim/defaults.py
hpvsim/hiv.py
hpvsim/immunity.py
hpvsim/interventions.py
hpvsim/misc.py
hpvsim/parameters.py
hpvsim/people.py
hpvsim/plotting.py
hpvsim/population.py
hpvsim/run.py
hpvsim/settings.py
hpvsim/sim.py
hpvsim/utils.py
hpvsim/version.py
hpvsim/data/__init__.py
hpvsim/data/downloaders.py
hpvsim/data/loaders.py
hpvsim/data/products_dx.csv
hpvsim/data/products_tx.csv
hpvsim/data/products_txvx.csv
hpvsim/data/products_vx.csv
hpvsim/data/test_downloaders.py
hpvsim/data/test_loaders.py
hpvsim/regression/pars_v0.2.6.json
hpvsim/regression/pars_v0.2.9.json
hpvsim/regression/pars_v0.3.0.json
hpvsim/regression/pars_v0.3.1.json
hpvsim-2.2.4.dist-info/licenses/LICENSE
hpvsim-2.2.4.dist-info/METADATA
hpvsim-2.2.4.dist-info/WHEEL
hpvsim-2.2.4.dist-info/top_level.txt
hpvsim-2.2.4.dist-info/RECORD
