Metadata-Version: 2.4
Name: hpvsim
Version: 2.2.4
Summary: HPVsim: Human Papillomavirus Simulator
Author: Robyn Stuart, Jamie Cohen, Cliff Kerr, Romesh Abeysuriya, Mariah Boudreau, Daniel Klein, Hao Hu
Maintainer-email: HPVsim Team <info@hpvsim.org>
License-Expression: MIT
Project-URL: Website, https://hpvsim.org
Project-URL: Source, https://github.com/institutefordiseasemodeling/hpvsim/
Keywords: HPV,human papillomavirus,cervical cancer,agent-based model,disease modeling,simulation
Classifier: Intended Audience :: Science/Research
Classifier: Operating System :: OS Independent
Classifier: Programming Language :: Python
Classifier: Topic :: Software Development :: Libraries :: Python Modules
Classifier: Development Status :: 5 - Production/Stable
Classifier: Programming Language :: Python :: 3.10
Classifier: Programming Language :: Python :: 3.11
Classifier: Programming Language :: Python :: 3.12
Requires-Python: >=3.9
License-File: LICENSE
Requires-Dist: numpy
Requires-Dist: scipy
Requires-Dist: pandas>=2.0.0
Requires-Dist: sciris>=3.0.0
Requires-Dist: matplotlib
Requires-Dist: seaborn
Requires-Dist: optuna
Dynamic: license-file
